ietf_reviewtool/__init__.py
ietf_reviewtool/__main__.py
ietf_reviewtool/agenda.py
ietf_reviewtool/boilerplate.py
ietf_reviewtool/doc.py
ietf_reviewtool/grammar.py
ietf_reviewtool/ietf_reviewtool.py
ietf_reviewtool/inclusive.py
ietf_reviewtool/metadata.py
ietf_reviewtool/references.py
ietf_reviewtool/review.py
ietf_reviewtool/util/__init__.py
ietf_reviewtool/util/docposition.py
ietf_reviewtool/util/fetch.py
ietf_reviewtool/util/format.py
ietf_reviewtool/util/text.py
ietf_reviewtool/util/utils.py
ietf_reviewtool-0.5.0.dist-info/METADATA
ietf_reviewtool-0.5.0.dist-info/WHEEL
ietf_reviewtool-0.5.0.dist-info/entry_points.txt
ietf_reviewtool-0.5.0.dist-info/licenses/LICENSE
ietf_reviewtool-0.5.0.dist-info/RECORD
