Metadata-Version: 2.4
Name: ietf-reviewtool
Version: 0.5.0
Summary: Review tool for IETF documents
License: GPL-2.0-only
License-File: LICENSE
Author: Lars Eggert
Author-email: lars@eggert.org
Requires-Python: >=3.11,<4
Classifier: License :: OSI Approved :: GNU General Public License v2 (GPLv2)
Classifier: Programming Language :: Python :: 3
Classifier: Programming Language :: Python :: 3.11
Classifier: Programming Language :: Python :: 3.12
Classifier: Programming Language :: Python :: 3.13
Classifier: Programming Language :: Python :: 3.14
Requires-Dist: PyYAML (>=5.4.1)
Requires-Dist: appdirs (>=1.4.4)
Requires-Dist: charset-normalizer (>=2.0.6)
Requires-Dist: click (>=7.1.2)
Requires-Dist: click-config-file (>=0.6.0,<0.7.0)
Requires-Dist: json-five (>=0.8.0)
Requires-Dist: language-tool-python (>=3.0.0)
Requires-Dist: num2words (>=0.5.10)
Requires-Dist: requests (>=2.28.2)
Requires-Dist: requests-cache (>=1.0.0)
Requires-Dist: setuptools (>=69.0.2,<81.0.0)
Requires-Dist: types-requests (>=2.32.4.20250913,<3.0.0.0)
Requires-Dist: urlextract (>=1.5.0)
Requires-Dist: urllib3 (>=1.26.15)
Project-URL: Homepage, https://github.com/larseggert/ietf-reviewtool
Project-URL: Repository, https://github.com/larseggert/ietf-reviewtool
